processingtools/EnvReco.py
processingtools/ProgressBar.py
processingtools/__init__.py
processingtools/functions.py
processingtools/version.py
processingtools/easteregg/__init__.py
processingtools/easteregg/this.py
processingtools/onnx_tools/ONNXProcess.py
processingtools/onnx_tools/__init__.py
processingtools/onnx_tools/onnx_function.py
processingtools/torch_tools/TorchProcess.py
processingtools/torch_tools/__init__.py
processingtools/torch_tools/torch_function.py
processingtools-0.5.1.dist-info/licenses/LICENSE
processingtools-0.5.1.dist-info/METADATA
processingtools-0.5.1.dist-info/WHEEL
processingtools-0.5.1.dist-info/top_level.txt
processingtools-0.5.1.dist-info/RECORD
