Metadata-Version: 2.4
Name: processingtools
Version: 0.5.1
Summary: A tool for image/video processing
Author-email: syy <ysy9997@gmail.com>
License: MIT
Requires-Python: >=3.7
License-File: LICENSE
Requires-Dist: opencv-python>=4.5.5.62
Requires-Dist: numpy>=1.19.4
Requires-Dist: matplotlib>=3.3.3
Dynamic: license-file
